README.md
setup.py
gc_data.egg-info/PKG-INFO
gc_data.egg-info/SOURCES.txt
gc_data.egg-info/dependency_links.txt
gc_data.egg-info/top_level.txt
src/__init__.py
src/city.py