Metadata-Version: 2.1
Name: gc-data
Version: 0.0.1a8
Summary: Open source extractor of the Canadian Government meteorological data.
Home-page: https://github.com/Mukki/gc-data
Author: Jeremy Bouchard
Author-email: mukki1996@gmail.com
License: UNKNOWN
Platform: UNKNOWN
Classifier: Programming Language :: Python :: 3.5
Classifier: Programming Language :: Python :: 3.6
Classifier: Programming Language :: Python :: 3.7
Classifier: License :: OSI Approved :: MIT License
Classifier: Operating System :: OS Independent
